pytest_porringer-0.1.1.dev8.dist-info/METADATA
pytest_porringer-0.1.1.dev8.dist-info/WHEEL
pytest_porringer-0.1.1.dev8.dist-info/entry_points.txt
pytest_porringer-0.1.1.dev8.dist-info/licenses/LICENSE.md
pytest_porringer/__init__.py
pytest_porringer/mock/__init__.py
pytest_porringer/mock/environment.py
pytest_porringer/plugin.py
pytest_porringer/py.typed
pytest_porringer/shared.py
pytest_porringer/tests.py
pytest_porringer/variants.py
pytest_porringer-0.1.1.dev8.dist-info/RECORD
