Metadata-Version: 2.1
Name: pytest-porringer
Version: 0.1.1.dev8
Home-page: https://github.com/Synodic-Software/Pytest-Porringer
Author-Email: Synodic Software <contact@synodic.software>
License: MIT
Project-URL: Homepage, https://github.com/Synodic-Software/Pytest-Porringer
Project-URL: Repository, https://github.com/Synodic-Software/Pytest-Porringer
Requires-Python: >=3.12
Requires-Dist: pydantic>=2.5.3
Requires-Dist: pytest-synodic>=0.0.0
Requires-Dist: porringer-core>=0.0.0
Requires-Dist: pytest>=7.4.4
Requires-Dist: pytest-mock>=3.12.0
